{
  "names": {
    "bns-zebranet": "BNS Zebranet",
    "da3ed6a45429278bac2666961289ca17ad86595d33b31037615d4b8e8f158bba": "Lisk Testnet",
    "ethereum-eip155-4": "Ethereum Testnet ::: Rinkeby"
  },
  "blockExplorers": {
    "bns-zebranet": null,
    "da3ed6a45429278bac2666961289ca17ad86595d33b31037615d4b8e8f158bba": "https://testnet-explorer.lisk.io/tx/",
    "ethereum-eip155-4": "https://rinkeby.etherscan.io/tx/"
  },
  "chains": [
    {
      "chainSpec": {
        "codecType": "bns",
        "bootstrapNodes": ["https://bns.zebranet.iov.one/"]
      },
      "faucetSpec": {
        "uri": "https://bns-faucet.zebranet.iov.one",
        "token": "IOV"
      }
    },
    {
      "chainSpec": {
        "codecType": "lsk",
        "bootstrapNodes": ["https://testnet.lisk.io"]
      }
    },
    {
      "chainSpec": {
        "codecType": "eth",
        "bootstrapNodes": ["https://rinkeby.infura.io", "https://api-rinkeby.etherscan.io/api"]
      }
    }
  ]
}
